config/__init__.py
config/config.py
models/__init__.py
models/job_post.py
models/resume.py
pdf_generation/__init__.py
pdf_generation/resume_pdf_generator.py
pdf_generation/resume_pdf_styles.py
prompts/__init__.py
prompts/prompts.py
services/__init__.py
services/background_runner.py
services/langchain_helpers.py
services/resume_improver.py
tests/__init__.py
tests/test_config.py
tests/test_models.py
tests/test_pdf_generation.py
tests/test_prompts.py
tests/test_services.py
tests/test_utils.py
utils/__init__.py
utils/file_handler.py
utils/pdf_generator.py
utils/resume_format_checker.py
utils/yaml_handler.py
ResumeGPT-2.1.dist-info/LICENSE
ResumeGPT-2.1.dist-info/METADATA
ResumeGPT-2.1.dist-info/WHEEL
ResumeGPT-2.1.dist-info/top_level.txt
ResumeGPT-2.1.dist-info/RECORD
