Metadata-Version: 2.1
Name: ResumeGPT
Version: 2.1
Summary: Tailor your resume to match any job posting effortlessly
Home-page: https://github.com/takline/ResumeGPT
Author: Tyler Kline
Author-email: Tyler Kline <tylerkline@gmail.com>
Maintainer-email: Tyler Kline <tylerkline@gmail.com>
Project-URL: Homepage, https://github.com/takline/ResumeGPT
Project-URL: Bug Tracker, https://github.com/takline/ResumeGPT/issues
Keywords: resume,job,application,automation,job search
Classifier: Development Status :: 4 - Beta
Classifier: Programming Language :: Python :: 3
Requires-Python: >=3.11
License-File: LICENSE
Requires-Dist: beautifulsoup4 >=4.12.3
Requires-Dist: configparser >=7.1.0
Requires-Dist: langchain >=0.2.11
Requires-Dist: langchain-openai >=0.1.6
Requires-Dist: langchain-core >=0.2.36
Requires-Dist: langchain-community >=0.2.10
Requires-Dist: pydantic >=2.7.1
Requires-Dist: reportlab >=4.2.2
Requires-Dist: requests >=2.32.3
Requires-Dist: ruamel.yaml >=0.18.6
Requires-Dist: pytest >=8.2.2
Requires-Dist: python-dateutil >=2.8.0
Requires-Dist: free-proxy >=1.1.1
Requires-Dist: Jinja2 >=3.1.4
Requires-Dist: PyYAML >=5.3.1
Requires-Dist: pytest-cov >=5.0.0
Provides-Extra: dev
Requires-Dist: pytest >=8.2.2 ; extra == 'dev'
